xchainpy_client/__init__.py
xchainpy_client/base_xchain_client.py
xchainpy_client/fee_rates.py
xchainpy_client/fees.py
xchainpy_client/interface.py
xchainpy_client/utxo_client.py
xchainpy_client/models/__init__.py
xchainpy_client/models/balance.py
xchainpy_client/models/tx_types.py
xchainpy_client/models/types.py
xchainpy_client-0.1.6.dist-info/LICENSE
xchainpy_client-0.1.6.dist-info/METADATA
xchainpy_client-0.1.6.dist-info/WHEEL
xchainpy_client-0.1.6.dist-info/top_level.txt
xchainpy_client-0.1.6.dist-info/RECORD
