Metadata-Version: 2.1
Name: xchainpy-client
Version: 0.1.6
Summary: A specification for a generalised interface for crypto wallets clients, to be used by XChainPY implementations. The client should not have any functionality to generate a key, instead, the `asgardex-crypto` library should be used to ensure cross-chain com
Home-page: https://github.com/xchainjs/xchainpy-lib/tree/main/xchainpy/xchainpy_client
Author: THORChain
Author-email: 
License: MIT
Keywords: THORChain,XChainpy,xchainpy_client
Platform: UNKNOWN
Classifier: Intended Audience :: Developers
Classifier: Topic :: Software Development :: Libraries :: Python Modules
Classifier: License :: OSI Approved :: MIT License
Classifier: Programming Language :: Python :: 3
Classifier: Programming Language :: Python :: 3.6
Classifier: Programming Language :: Python :: 3.7
Classifier: Programming Language :: Python
License-File: LICENSE
Requires-Dist: xchainpy-util (>=0.1.8)
Requires-Dist: xchainpy-crypto (>=0.1.7)
Requires-Dist: http3 (>=0.6.7)
